topmostp/__init__.py
topmostp/helper.py
topmostp/main.py
topmostp-0.1.10.dist-info/METADATA
topmostp-0.1.10.dist-info/WHEEL
topmostp-0.1.10.dist-info/entry_points.txt
topmostp-0.1.10.dist-info/licenses/LICENSE
topmostp-0.1.10.dist-info/RECORD
