Metadata-Version: 2.4
Name: topmostp
Version: 0.1.10
Summary: A simple CLI tool to retrieve the N top most used ports
License: MIT
License-File: LICENSE
Author: SecSI
Author-email: dev@secsi.io
Requires-Python: >=3.11,<3.14
Classifier: License :: OSI Approved :: MIT License
Classifier: Programming Language :: Python :: 3
Classifier: Programming Language :: Python :: 3.11
Classifier: Programming Language :: Python :: 3.12
Classifier: Programming Language :: Python :: 3.13
Requires-Dist: certifi (==2025.7.14)
Requires-Dist: click (==8.2.1)
Requires-Dist: idna (==3.10)
Requires-Dist: requests (>=2.32.4,<3.0.0)
Requires-Dist: typer (==0.9.0)
Requires-Dist: typing_extensions (==4.14.1)
Project-URL: Repository, https://github.com/cybersecsi/topmostp
